dcmstudyclean/Archive.py
dcmstudyclean/InsertOutput.py
dcmstudyclean/NamingConvention.py
dcmstudyclean/RecordStudyInfo.py
dcmstudyclean/StudyImage.py
dcmstudyclean/StudyImageAbstract.py
dcmstudyclean/StudyPipeline.py
dcmstudyclean/__init__.py
dcmstudyclean/script.py
dcmstudyclean-0.2.0.dist-info/entry_points.txt
dcmstudyclean-0.2.0.dist-info/WHEEL
dcmstudyclean-0.2.0.dist-info/METADATA
dcmstudyclean-0.2.0.dist-info/RECORD
